paperminer/__init__.py
paperminer/converter.py
paperminer/layout.py
paperminer-0.1.dist-info/LICENSE
paperminer-0.1.dist-info/METADATA
paperminer-0.1.dist-info/WHEEL
paperminer-0.1.dist-info/top_level.txt
paperminer-0.1.dist-info/RECORD
